arxiv_source/.DS_Store
arxiv_source/__init__.py
arxiv_source/arxiv.py
arxiv_source-0.1.3.dist-info/LICENSE
arxiv_source-0.1.3.dist-info/METADATA
arxiv_source-0.1.3.dist-info/WHEEL
arxiv_source-0.1.3.dist-info/RECORD
